multimodule.py
multimodule-0.8.dist-info/LICENSE
multimodule-0.8.dist-info/WHEEL
multimodule-0.8.dist-info/METADATA
multimodule-0.8.dist-info/RECORD
